{
  "douga": ["动画", "-141", "-908"],
  "fanju": [
    "番剧",
    "-141",
    "-140"
  ],
  "music": [
    "音乐",
    "-141",
    "-266"
  ],
  "dance": [
    "舞蹈",
    "-141",
    "-461"
  ],
  "game": [
    "游戏",
    "-141",
    "-203"
  ],
  "technology": [
    "科技",
    "-141",
    "-525"
  ],
  "life": [
    "生活",
    "-141",
    "-970"
  ],
  "kichiku": [
    "鬼畜",
    "-141",
    "-332"
  ],
  "fashion": [
    "时尚",
    "-141",
    "-718"
  ],
  "ad": [
    "广告",
    "-141",
    "-1228"
  ],
  "ent": [
    "娱乐",
    "-141",
    "-1032"
  ],
  "film": [
    "影视",
    "-141",
    "-396"
  ]
}